{
    "alioth": 198365,
    "sky": 20916,
    "cancunf": 6498,
    "apollo": 22626,
    "RMX2020": 23394,
    "beryllium": 165716,
    "surya": 60494,
    "RMX2001L1": 11375,
    "lisa": 142796,
    "sweet": 327520,
    "aston": 18240,
    "lunaa": 13326,
    "pipa": 12213,
    "gauguin": 42611,
    "salaa": 8763,
    "cepheus": 91502,
    "oscar": 18830,
    "zeus": 9969,
    "benz": 819,
    "sunny": 68922,
    "cupid": 12241,
    "peridot": 9385,
    "porsche": 15114,
    "davinci": 63597,
    "munch": 20321,
    "r5x": 7667,
    "tundra": 3447,
    "mido": 26248,
    "martini": 22834,
    "beyondx": 3609,
    "d1": 3416,
    "ginkgo": 147203,
    "beyond1lte": 10041,
    "d1x": 1236,
    "vayu": 74963,
    "marble": 21698,
    "diting": 5968,
    "beyond2lte": 10641,
    "d2x": 5091,
    "miatoll": 84940,
    "bitra": 4908,
    "d2s": 8343,
    "pdx206": 5375,
    "guamp": 3688,
    "toco": 20897,
    "courbet": 26014,
    "G": 4754,
    "f62": 4685,
    "beyond0lte": 8491,
    "grus": 4126,
    "cheetah": 2449,
    "violet": 25463,
    "citrus": 4906,
    "coral": 2495,
    "yogurt": 1722,
    "lime": 7706,
    "spaced": 2399,
    "flame": 4106,
    "dubai": 2230,
    "panther": 3954,
    "lancelot": 11705,
    "hotdog": 1464,
    "starlte": 1704,
    "star2lte": 2103,
    "whyred": 5659,
    "RMX1941": 2815,
    "crownlte": 1742,
    "hotdogg": 1107,
    "juice": 8761,
    "mojito": 22051
}